agksWrapper/__init__.py
agksWrapper/agsk_warpper.py
AutogluonToScikitWrapper-0.0.1.dist-info/METADATA
AutogluonToScikitWrapper-0.0.1.dist-info/WHEEL
AutogluonToScikitWrapper-0.0.1.dist-info/top_level.txt
AutogluonToScikitWrapper-0.0.1.dist-info/RECORD
